nonebot_plugin_dcqq_relay/__init__.py
nonebot_plugin_dcqq_relay/config.py
nonebot_plugin_dcqq_relay/dc_to_qq.py
nonebot_plugin_dcqq_relay/migrations/5fb7a7432778_change_dcid_type.py
nonebot_plugin_dcqq_relay/migrations/ca5c07252665_init_db.py
nonebot_plugin_dcqq_relay/model.py
nonebot_plugin_dcqq_relay/qq_emoji_dict.py
nonebot_plugin_dcqq_relay/qq_to_dc.py
nonebot_plugin_dcqq_relay/utils.py
nonebot_plugin_dcqq_relay-1.2.0.dist-info/METADATA
nonebot_plugin_dcqq_relay-1.2.0.dist-info/WHEEL
nonebot_plugin_dcqq_relay-1.2.0.dist-info/licenses/LICENSE
nonebot_plugin_dcqq_relay-1.2.0.dist-info/RECORD
