Metadata-Version: 2.4
Name: nonebot-plugin-dcqq-relay
Version: 1.2.0
Summary: 在QQ群与 Discord 之间同步消息的 nonebot2 插件
License: MIT
License-File: LICENSE
Author: Autuamn_End
Author-email: autuamn@qq.com
Requires-Python: >=3.9,<4.0
Classifier: License :: OSI Approved :: MIT License
Classifier: Programming Language :: Python :: 3
Classifier: Programming Language :: Python :: 3.9
Classifier: Programming Language :: Python :: 3.10
Classifier: Programming Language :: Python :: 3.11
Classifier: Programming Language :: Python :: 3.12
Classifier: Programming Language :: Python :: 3.13
Classifier: Programming Language :: Python :: 3.14
Requires-Dist: audioop-lts ; python_version >= "3.13" and python_version < "4.0"
Requires-Dist: filetype (>=1.2.0,<2.0.0)
Requires-Dist: nonebot-adapter-discord (>=0.1.8,<0.2.0)
Requires-Dist: nonebot-adapter-onebot (>=2.4.3,<3.0.0)
Requires-Dist: nonebot-plugin-localstore (>=0.7.4,<0.8.0)
Requires-Dist: nonebot-plugin-orm[default] (>=0.8.1,<0.9.0)
Requires-Dist: nonebot2[aiohttp,fastapi] (>=2.2.1,<3.0.0)
Requires-Dist: pydub (>=0.25.1,<0.26.0)
Requires-Dist: pysilk-mod (>=1.6.4,<2.0.0)
